pytea/__init__.py
pytea/_tea.c
pytea/_tea.cpython-38-darwin.so
pytea/_tea.pyx
pytea/pytea.py
pytea/tea.pxd
pytea2-0.2.0.dist-info/LICENSE
pytea2-0.2.0.dist-info/METADATA
pytea2-0.2.0.dist-info/WHEEL
pytea2-0.2.0.dist-info/top_level.txt
pytea2-0.2.0.dist-info/RECORD
