Metadata-Version: 2.1
Name: pytea2
Version: 0.2.0
Summary: tea encrypt and decrypt
Home-page: https://github.com/synodriver/pytea
Author: synodriver
Author-email: diguohuangjiajinweijun@gmail.com
License: GPLv3
Keywords: tea,encrypt,decrypt
Platform: UNKNOWN
Classifier: Development Status :: 4 - Beta
Classifier: Operating System :: OS Independent
Classifier: License :: OSI Approved :: GNU General Public License v3 (GPLv3)
Classifier: Topic :: Security :: Cryptography
Classifier: Programming Language :: C
Classifier: Programming Language :: Cython
Classifier: Programming Language :: Python
Classifier: Programming Language :: Python :: 3.6
Classifier: Programming Language :: Python :: 3.7
Classifier: Programming Language :: Python :: 3.8
Classifier: Programming Language :: Python :: 3.9
Classifier: Programming Language :: Python :: 3.10
Classifier: Programming Language :: Python :: Implementation :: CPython
Requires-Python: >=3.6
License-File: LICENSE
Requires-Dist: cython
